setup.py
devdoo/__init__.py
devdoo/console.py
devdoo/database.py
devdoo/datafilter.py
devdoo/datarest.py
devdoo/datarest_db.py
devdoo/datatypes.py
devdoo/decode_types.py
devdoo/devdoo_brokers.py
devdoo/devdoo_database.py
devdoo/devdoo_services.py
devdoo/i18n.py
devdoo/service.py
devdoo/service_db.py
devdoo/status.py
devdoo/validate.py
packagetest60.egg-info/PKG-INFO
packagetest60.egg-info/SOURCES.txt
packagetest60.egg-info/dependency_links.txt
packagetest60.egg-info/not-zip-safe
packagetest60.egg-info/top_level.txt